pulumi_mysql/__init__.py
pulumi_mysql/_utilities.py
pulumi_mysql/database.py
pulumi_mysql/grant.py
pulumi_mysql/provider.py
pulumi_mysql/pulumi-plugin.json
pulumi_mysql/py.typed
pulumi_mysql/role.py
pulumi_mysql/user.py
pulumi_mysql/user_password.py
pulumi_mysql/config/__init__.py
pulumi_mysql/config/__init__.pyi
pulumi_mysql/config/vars.py
pulumi_mysql-3.2.13.dist-info/METADATA
pulumi_mysql-3.2.13.dist-info/WHEEL
pulumi_mysql-3.2.13.dist-info/top_level.txt
pulumi_mysql-3.2.13.dist-info/RECORD
